{
    "/js/app.js": "/js/app.js",
    "/css/app.css": "/css/app.css",
    "/0.9c233d756ad2811eedc2.hot-update.js": "/0.9c233d756ad2811eedc2.hot-update.js",
    "/0.61cc75b2357a365885ae.hot-update.js": "/0.61cc75b2357a365885ae.hot-update.js",
    "/0.94520a92a0dc98b8eecf.hot-update.js": "/0.94520a92a0dc98b8eecf.hot-update.js",
    "/0.df88a472c2c60b18fa00.hot-update.js": "/0.df88a472c2c60b18fa00.hot-update.js",
    "/0.504eb1014d6d63fccffa.hot-update.js": "/0.504eb1014d6d63fccffa.hot-update.js",
    "/0.21523b8cc603e391a99c.hot-update.js": "/0.21523b8cc603e391a99c.hot-update.js",
    "/0.084749258b6fc8a12f38.hot-update.js": "/0.084749258b6fc8a12f38.hot-update.js",
    "/0.44d7f41cf7bf56356131.hot-update.js": "/0.44d7f41cf7bf56356131.hot-update.js",
    "/0.fda6ff721ad551bd962f.hot-update.js": "/0.fda6ff721ad551bd962f.hot-update.js",
    "/0.cda23008622a3d18ff77.hot-update.js": "/0.cda23008622a3d18ff77.hot-update.js",
    "/0.b440ecb403701722dbdd.hot-update.js": "/0.b440ecb403701722dbdd.hot-update.js",
    "/0.c7d6401150237b088dd2.hot-update.js": "/0.c7d6401150237b088dd2.hot-update.js",
    "/0.c17f1fdf38a924ffa092.hot-update.js": "/0.c17f1fdf38a924ffa092.hot-update.js",
    "/0.7e7f345bb935240d4742.hot-update.js": "/0.7e7f345bb935240d4742.hot-update.js",
    "/0.8663375ab8240bd2fd3f.hot-update.js": "/0.8663375ab8240bd2fd3f.hot-update.js",
    "/0.6e4d9d729f7e68a2b753.hot-update.js": "/0.6e4d9d729f7e68a2b753.hot-update.js",
    "/0.5afa6bc61f0d76155555.hot-update.js": "/0.5afa6bc61f0d76155555.hot-update.js",
    "/0.df01c66fcab07f5f652b.hot-update.js": "/0.df01c66fcab07f5f652b.hot-update.js",
    "/0.c46458934cfc31b7527c.hot-update.js": "/0.c46458934cfc31b7527c.hot-update.js",
    "/0.6be31843ece52c2ce77e.hot-update.js": "/0.6be31843ece52c2ce77e.hot-update.js",
    "/0.7eadf740878c92e89cd7.hot-update.js": "/0.7eadf740878c92e89cd7.hot-update.js",
    "/0.a04bd702e2feb3625ef5.hot-update.js": "/0.a04bd702e2feb3625ef5.hot-update.js",
    "/0.cf4cee9be7260cad5d48.hot-update.js": "/0.cf4cee9be7260cad5d48.hot-update.js",
    "/0.03e1c9e1cb7a13347ae3.hot-update.js": "/0.03e1c9e1cb7a13347ae3.hot-update.js",
    "/0.f969a589a04af79b5369.hot-update.js": "/0.f969a589a04af79b5369.hot-update.js",
    "/0.1fa4569c90aeef0993ea.hot-update.js": "/0.1fa4569c90aeef0993ea.hot-update.js",
    "/0.73b91698734d2eaea2e0.hot-update.js": "/0.73b91698734d2eaea2e0.hot-update.js",
    "/0.75c81e774642504db802.hot-update.js": "/0.75c81e774642504db802.hot-update.js",
    "/0.02e2c90cf8a869904312.hot-update.js": "/0.02e2c90cf8a869904312.hot-update.js",
    "/0.c316f3923aaf151f223b.hot-update.js": "/0.c316f3923aaf151f223b.hot-update.js",
    "/0.2ce3b53b7d67083499fb.hot-update.js": "/0.2ce3b53b7d67083499fb.hot-update.js",
    "/0.573ce9841258e37127e6.hot-update.js": "/0.573ce9841258e37127e6.hot-update.js",
    "/0.c4b9ef9afaa72813f215.hot-update.js": "/0.c4b9ef9afaa72813f215.hot-update.js",
    "/0.e4acb9f23ae1d3c36f53.hot-update.js": "/0.e4acb9f23ae1d3c36f53.hot-update.js",
    "/0.6f8a337d38d6446c39f1.hot-update.js": "/0.6f8a337d38d6446c39f1.hot-update.js",
    "/0.ea949870b60760efc602.hot-update.js": "/0.ea949870b60760efc602.hot-update.js",
    "/0.f655fa5c565fd61d927f.hot-update.js": "/0.f655fa5c565fd61d927f.hot-update.js",
    "/0.2c3f73d8ab24e6c4cc08.hot-update.js": "/0.2c3f73d8ab24e6c4cc08.hot-update.js"
}
