{
    "/js/app.js": "/js/app.js",
    "/css/app.css": "/css/app.css",
    "/0.d4a3a04251dcd1bb5b4b.hot-update.js": "/0.d4a3a04251dcd1bb5b4b.hot-update.js",
    "/0.4b356eff4dc85278897f.hot-update.js": "/0.4b356eff4dc85278897f.hot-update.js",
    "/0.e0fe1f2cfe65e0497fac.hot-update.js": "/0.e0fe1f2cfe65e0497fac.hot-update.js",
    "/0.2274b13c87593e520f71.hot-update.js": "/0.2274b13c87593e520f71.hot-update.js",
    "/0.518b4009ebc1a50fccdd.hot-update.js": "/0.518b4009ebc1a50fccdd.hot-update.js",
    "/0.ae64f99695ad8a8e9f6a.hot-update.js": "/0.ae64f99695ad8a8e9f6a.hot-update.js",
    "/0.0866caf3a27ef1e7611f.hot-update.js": "/0.0866caf3a27ef1e7611f.hot-update.js",
    "/0.586e73536b1aac12c206.hot-update.js": "/0.586e73536b1aac12c206.hot-update.js",
    "/0.ae1b9ccca4366683603f.hot-update.js": "/0.ae1b9ccca4366683603f.hot-update.js",
    "/0.23ed1a1b9e279ef4d8eb.hot-update.js": "/0.23ed1a1b9e279ef4d8eb.hot-update.js",
    "/0.04d79f358b916be3ec9b.hot-update.js": "/0.04d79f358b916be3ec9b.hot-update.js",
    "/0.f4a3f4df850034c1f510.hot-update.js": "/0.f4a3f4df850034c1f510.hot-update.js"
}
