{
    "/js/app.js": "/js/app.js",
    "/js/manifest.js": "/js/manifest.js",
    "/js/vendor.js": "/js/vendor.js",
    "/js/app.45997601434071276ede.hot-update.js": "/js/app.45997601434071276ede.hot-update.js",
    "/js/app.c67b47f113e8cbd5f550.hot-update.js": "/js/app.c67b47f113e8cbd5f550.hot-update.js",
    "/js/app.4a7f322e28d1423fc5d4.hot-update.js": "/js/app.4a7f322e28d1423fc5d4.hot-update.js",
    "/js/app.acb988e011e083e8ff12.hot-update.js": "/js/app.acb988e011e083e8ff12.hot-update.js",
    "/js/app.c053021c1592ec8722e3.hot-update.js": "/js/app.c053021c1592ec8722e3.hot-update.js",
    "/js/app.da2aedbd5daba959fc84.hot-update.js": "/js/app.da2aedbd5daba959fc84.hot-update.js",
    "/js/app.6ce5408c7cf351d8d40b.hot-update.js": "/js/app.6ce5408c7cf351d8d40b.hot-update.js",
    "/js/app.17a36f174153a06a0cf2.hot-update.js": "/js/app.17a36f174153a06a0cf2.hot-update.js",
    "/js/app.8ecfadcfc2f50d362db0.hot-update.js": "/js/app.8ecfadcfc2f50d362db0.hot-update.js",
    "/js/app.9097aa8cd713d97fa246.hot-update.js": "/js/app.9097aa8cd713d97fa246.hot-update.js",
    "/js/app.304c6a1765169fab596c.hot-update.js": "/js/app.304c6a1765169fab596c.hot-update.js",
    "/js/app.8ca56c9b27cbdab249cb.hot-update.js": "/js/app.8ca56c9b27cbdab249cb.hot-update.js"
}
